mmreact/__init__.py
mmreact-0.0.1.dev0.dist-info/METADATA
mmreact-0.0.1.dev0.dist-info/WHEEL
mmreact-0.0.1.dev0.dist-info/top_level.txt
mmreact-0.0.1.dev0.dist-info/RECORD
