Metadata-Version: 2.1
Name: mmreact
Version: 0.0.1.dev0
Summary: MM-REACT: Prompting ChatGPT for Multimodal Reasoning and Action
Author: Shadow Walker
License: UNKNOWN
Keywords: mmreact
Platform: UNKNOWN
Classifier: Programming Language :: Python :: 3
Classifier: Programming Language :: Python :: 3.8
Classifier: Programming Language :: Python :: 3.9
Classifier: Programming Language :: Python :: 3.10
Requires-Dist: torch
